pywrap/__init__.py
pywrap/pywrap.py
PygameWrap-0.0.5.dist-info/LICENSE.txt
PygameWrap-0.0.5.dist-info/METADATA
PygameWrap-0.0.5.dist-info/WHEEL
PygameWrap-0.0.5.dist-info/top_level.txt
PygameWrap-0.0.5.dist-info/RECORD
