Metadata-Version: 2.1
Name: PygameWrap
Version: 0.0.5
Summary: small wrapper/toolkit for writing games with pygame
Home-page: https://github.com/MoserMichael/pygamewrap
Author: Michael Moser
Author-email: moser.michael@gmail.com
License: MIT
Project-URL: Bug Tracker, https://github.com/MoserMichael/pygamewrap/issues
Keywords: games; pygame; toolkit fo games
Platform: UNKNOWN
Classifier: Programming Language :: Python :: 3
Classifier: License :: OSI Approved :: MIT License
Classifier: Operating System :: OS Independent
Classifier: Topic :: Games/Entertainment
Classifier: Intended Audience :: Developers
Classifier: Intended Audience :: Education
Requires-Python: >=3.6
Requires-Dist: pygame (==2.0.2)
